ml_liv/__init__.py
ml_liv/experiment.py
ml_liv-0.0.1.dist-info/METADATA
ml_liv-0.0.1.dist-info/WHEEL
ml_liv-0.0.1.dist-info/top_level.txt
ml_liv-0.0.1.dist-info/RECORD
